d1_dev/__init__.py
d1_dev/clean-tree.py
d1_dev/devpi-install.sh
d1_dev/devpi-server.sh
d1_dev/devpi-settings-template.sh
d1_dev/devpi-upload.sh
d1_dev/find-files.py
d1_dev/git-verify-wheel.py
d1_dev/pip-update-all.py
d1_dev/pycharm-fix-coverage-paths.py
d1_dev/setup-all.py
d1_dev/src-cleanup.py
d1_dev/src-find-dependencies.py
d1_dev/src-format-docstrings.py
d1_dev/src-format.py
d1_dev/src-insert-import.py
d1_dev/src-list-tests.py
d1_dev/src-missing-imports.py
d1_dev/src-print-redbaron-tree.py
d1_dev/src-remove-import-alias.py
d1_dev/src-remove-unused-imports.py
d1_dev/src-renumber-tests.py
d1_dev/src-sync-dependencies.py
d1_dev/syspath.py
d1_dev/trigger-pre-commit.py
d1_dev/update-requirements-txt.py
d1_dev/util.py
dataone.dev-3.5.2.dist-info/METADATA
dataone.dev-3.5.2.dist-info/WHEEL
dataone.dev-3.5.2.dist-info/top_level.txt
dataone.dev-3.5.2.dist-info/RECORD
