Metadata-Version: 2.1
Name: dataone.dev
Version: 3.5.2
Summary: DataONE developer tools
Home-page: https://github.com/DataONEorg/d1_dev
Author: DataONE Project
Author-email: developers@dataone.org
License: Apache License, Version 2.0
Keywords: DataONE python
Classifier: Development Status :: 5 - Production/Stable
Classifier: Intended Audience :: Developers
Classifier: Topic :: Scientific/Engineering
Classifier: License :: OSI Approved :: Apache Software License
Classifier: Programming Language :: Python :: 3
Classifier: Programming Language :: Python :: 3.7
Requires-Dist: baron (>=0.10.1)
Requires-Dist: pip (>=23.1.2)
Requires-Dist: redbaron (>=0.9.2)
Requires-Dist: sphinx
Requires-Dist: sphinx-better-theme
Requires-Dist: python-xlib
Requires-Dist: black
Requires-Dist: isort
